{
    
  "ticket": [
    {
      "id": 1,
      "name": "International Tickets",
      "price": 1199,
      "imgName": "Ticket 1.png"
    },
    {
      "id": 2,
      "name": "National Tickets",
      "price": 1133,
      "imgName": "Ticket 2.png"
    }
    ],
  "music": [
      {
        "id": 3,
        "name": "Album 1",
        "price": 1299,
        "imgName": "Album 1.jpg"
      },
      {
        "id": 4,
        "name": "Album 2",
        "price": 1499,
        "imgName": "Album 2.jpg"
      },
      {
        "id": 5,
        "name": "Album 3",
        "price": 999,
        "imgName": "Album 3.png"
      },
      {
        "id": 6,
        "name": "Album 4",
        "price": 1999,
        "imgName": "Album 4.png"
      }
    ],
    "merch": [
      {
        "id": 7,
        "name": "T-Shirt",
        "price": 1999,
        "imgName": "Shirt.png"
      },
      {
        "id": 8,
        "name": "Coffee Cup",
        "price": 699,
        "imgName": "Cofee.jpg"
      }
    ]
  }